examples/__init__.py
examples/ray_ddp_example.py
examples/ray_ddp_sharded_example.py
examples/ray_ddp_tune.py
examples/ray_horovod_example.py
ray_lightning/__init__.py
ray_lightning/ray_ddp.py
ray_lightning/ray_ddp_sharded.py
ray_lightning/ray_horovod.py
ray_lightning/session.py
ray_lightning/tune.py
ray_lightning/util.py
ray_lightning/accelerators/__init__.py
ray_lightning/accelerators/delayed_gpu_accelerator.py
ray_lightning/examples/__init__.py
ray_lightning/examples/ray_ddp_example.py
ray_lightning/examples/ray_ddp_sharded_example.py
ray_lightning/examples/ray_ddp_tune.py
ray_lightning/examples/ray_horovod_example.py
ray_lightning/launchers/__init__.py
ray_lightning/launchers/ray_horovod_launcher.py
ray_lightning/launchers/ray_launcher.py
ray_lightning/launchers/utils.py
ray_lightning/tests/__init__.py
ray_lightning/tests/test_client.py
ray_lightning/tests/test_client_2.py
ray_lightning/tests/test_client_3.py
ray_lightning/tests/test_ddp.py
ray_lightning/tests/test_ddp_gpu.py
ray_lightning/tests/test_ddp_sharded.py
ray_lightning/tests/test_horovod.py
ray_lightning/tests/test_tune.py
ray_lightning/tests/utils.py
ray_lightning-0.3.0.dist-info/LICENSE
ray_lightning-0.3.0.dist-info/METADATA
ray_lightning-0.3.0.dist-info/WHEEL
ray_lightning-0.3.0.dist-info/top_level.txt
ray_lightning-0.3.0.dist-info/RECORD
