Metadata-Version: 2.1
Name: ray-lightning
Version: 0.3.0
Summary: Ray distributed strategies for Pytorch Lightning.
Home-page: https://github.com/ray-project/ray_lightning_accelerators
Author: Ray Team
License: UNKNOWN
Platform: UNKNOWN
License-File: LICENSE
Requires-Dist: pytorch-lightning (==1.6.*)
Requires-Dist: ray
